fastapi_apscheduler4/__init__.py
fastapi_apscheduler4/app.py
fastapi_apscheduler4/apscheduler_builder.py
fastapi_apscheduler4/config.py
fastapi_apscheduler4/constants.py
fastapi_apscheduler4/dtos.py
fastapi_apscheduler4/errors.py
fastapi_apscheduler4/py.typed
fastapi_apscheduler4/scheduler.py
fastapi_apscheduler4/schemas.py
fastapi_apscheduler4/utils.py
fastapi_apscheduler4/routers/__init__.py
fastapi_apscheduler4/routers/deps.py
fastapi_apscheduler4/routers/schedules.py
fastapi_apscheduler4/routers/tasks.py
fastapi_apscheduler4-0.3.0.dist-info/METADATA
fastapi_apscheduler4-0.3.0.dist-info/WHEEL
fastapi_apscheduler4-0.3.0.dist-info/licenses/LICENSE
fastapi_apscheduler4-0.3.0.dist-info/RECORD
